ssr/__init__.py
ssr/bundler.py
ssr/server.py
ssr/settings.py
ssr/template.py
ssr/utils.py
ssr/worker.py
ssr/backends/javascript.py
ssr/management/commands/bundle.py
ssr/scripts/bundler.mjs
ssr/scripts/server.mjs
ssr/scripts/utils.mjs
ssr/scripts/entries/client.js
ssr/scripts/entries/server.js
ssr/scripts/react/client.js
ssr/scripts/react/server.js
django_parcel_ssr-0.7.0.dist-info/METADATA
django_parcel_ssr-0.7.0.dist-info/WHEEL
django_parcel_ssr-0.7.0.dist-info/top_level.txt
django_parcel_ssr-0.7.0.dist-info/RECORD
