Metadata-Version: 2.1
Name: django-parcel-ssr
Version: 0.7.0
Summary: Django server side rendering, powered by Parcel bundler
Home-page: https://github.com/malj/django-parcel-ssr
Author: Luka Maljic
Author-email: luka@maljic.com
License: UNKNOWN
Platform: UNKNOWN
Classifier: Programming Language :: Python :: 3
Classifier: License :: OSI Approved :: MIT License
Classifier: Operating System :: OS Independent
Requires-Dist: django
Requires-Dist: requests-unixsocket
